{"nombre": "DE AMAICHA", "distancia_km": 17.9, "puntos": [{"lat": -26.70892, "lng": -65.79676, "km": 0.0}, {"lat": -26.70775, "lng": -65.79804, "km": 0.2}, {"lat": -26.70659, "lng": -65.79931, "km": 0.4}, {"lat": -26.70543, "lng": -65.80059, "km": 0.5}, {"lat": -26.70427, "lng": -65.80186, "km": 0.7}, {"lat": -26.7031, "lng": -65.80313, "km": 0.9}, {"lat": -26.70194, "lng": -65.80441, "km": 1.1}, {"lat": -26.70078, "lng": -65.80568, "km": 1.3}, {"lat": -26.69962, "lng": -65.80696, "km": 1.4}, {"lat": -26.69846, "lng": -65.80823, "km": 1.6}, {"lat": -26.69729, "lng": -65.8095, "km": 1.8}, {"lat": -26.69613, "lng": -65.81078, "km": 2.0}, {"lat": -26.69497, "lng": -65.81205, "km": 2.2}, {"lat": -26.69381, "lng": -65.81333, "km": 2.4}, {"lat": -26.69265, "lng": -65.8146, "km": 2.5}, {"lat": -26.69148, "lng": -65.81587, "km": 2.7}, {"lat": -26.69032, "lng": -65.81715, "km": 2.9}, {"lat": -26.68916, "lng": -65.81842, "km": 3.1}, {"lat": -26.688, "lng": -65.8197, "km": 3.3}, {"lat": -26.68683, "lng": -65.82097, "km": 3.4}, {"lat": -26.68567, "lng": -65.82224, "km": 3.6}, {"lat": -26.68451, "lng": -65.82352, "km": 3.8}, {"lat": -26.68335, "lng": -65.82479, "km": 4.0}, {"lat": -26.68219, "lng": -65.82607, "km": 4.2}, {"lat": -26.68102, "lng": -65.82734, "km": 4.3}, {"lat": -26.67986, "lng": -65.82861, "km": 4.5}, {"lat": -26.6787, "lng": -65.82989, "km": 4.7}, {"lat": -26.67754, "lng": -65.83116, "km": 4.9}, {"lat": -26.67638, "lng": -65.83244, "km": 5.1}, {"lat": -26.67521, "lng": -65.83371, "km": 5.2}, {"lat": -26.67405, "lng": -65.83499, "km": 5.4}, {"lat": -26.67289, "lng": -65.83626, "km": 5.6}, {"lat": -26.67173, "lng": -65.83753, "km": 5.8}, {"lat": -26.67057, "lng": -65.83881, "km": 6.0}, {"lat": -26.6694, "lng": -65.84008, "km": 6.2}, {"lat": -26.66824, "lng": -65.84136, "km": 6.3}, {"lat": -26.66708, "lng": -65.84263, "km": 6.5}, {"lat": -26.66592, "lng": -65.8439, "km": 6.7}, {"lat": -26.66475, "lng": -65.84518, "km": 6.9}, {"lat": -26.66359, "lng": -65.84645, "km": 7.1}, {"lat": -26.66243, "lng": -65.84773, "km": 7.2}, {"lat": -26.66127, "lng": -65.849, "km": 7.4}, {"lat": -26.66011, "lng": -65.85027, "km": 7.6}, {"lat": -26.65894, "lng": -65.85155, "km": 7.8}, {"lat": -26.65778, "lng": -65.85282, "km": 8.0}, {"lat": -26.65662, "lng": -65.8541, "km": 8.1}, {"lat": -26.65546, "lng": -65.85537, "km": 8.3}, {"lat": -26.6543, "lng": -65.85664, "km": 8.5}, {"lat": -26.65313, "lng": -65.85792, "km": 8.7}, {"lat": -26.65197, "lng": -65.85919, "km": 8.9}, {"lat": -26.65081, "lng": -65.86047, "km": 9.0}, {"lat": -26.64965, "lng": -65.86174, "km": 9.2}, {"lat": -26.64849, "lng": -65.86301, "km": 9.4}, {"lat": -26.64732, "lng": -65.86429, "km": 9.6}, {"lat": -26.64616, "lng": -65.86556, "km": 9.8}, {"lat": -26.645, "lng": -65.86684, "km": 10.0}, {"lat": -26.64384, "lng": -65.86811, "km": 10.1}, {"lat": -26.64267, "lng": -65.86938, "km": 10.3}, {"lat": -26.64151, "lng": -65.87066, "km": 10.5}, {"lat": -26.64035, "lng": -65.87193, "km": 10.7}, {"lat": -26.63919, "lng": -65.87321, "km": 10.9}, {"lat": -26.63803, "lng": -65.87448, "km": 11.0}, {"lat": -26.63686, "lng": -65.87576, "km": 11.2}, {"lat": -26.6357, "lng": -65.87703, "km": 11.4}, {"lat": -26.63454, "lng": -65.8783, "km": 11.6}, {"lat": -26.63338, "lng": -65.87958, "km": 11.8}, {"lat": -26.63222, "lng": -65.88085, "km": 11.9}, {"lat": -26.63105, "lng": -65.88213, "km": 12.1}, {"lat": -26.62989, "lng": -65.8834, "km": 12.3}, {"lat": -26.62873, "lng": -65.88467, "km": 12.5}, {"lat": -26.62757, "lng": -65.88595, "km": 12.7}, {"lat": -26.6264, "lng": -65.88722, "km": 12.8}, {"lat": -26.62524, "lng": -65.8885, "km": 13.0}, {"lat": -26.62408, "lng": -65.88977, "km": 13.2}, {"lat": -26.62292, "lng": -65.89104, "km": 13.4}, {"lat": -26.62176, "lng": -65.89232, "km": 13.6}, {"lat": -26.62059, "lng": -65.89359, "km": 13.7}, {"lat": -26.61943, "lng": -65.89487, "km": 13.9}, {"lat": -26.61827, "lng": -65.89614, "km": 14.1}, {"lat": -26.61711, "lng": -65.89741, "km": 14.3}, {"lat": -26.61595, "lng": -65.89869, "km": 14.5}, {"lat": -26.61478, "lng": -65.89996, "km": 14.7}, {"lat": -26.61362, "lng": -65.90124, "km": 14.8}, {"lat": -26.61246, "lng": -65.90251, "km": 15.0}, {"lat": -26.6113, "lng": -65.90378, "km": 15.2}, {"lat": -26.61014, "lng": -65.90506, "km": 15.4}, {"lat": -26.60897, "lng": -65.90633, "km": 15.6}, {"lat": -26.60781, "lng": -65.90761, "km": 15.7}, {"lat": -26.60665, "lng": -65.90888, "km": 15.9}, {"lat": -26.60549, "lng": -65.91015, "km": 16.1}, {"lat": -26.60432, "lng": -65.91143, "km": 16.3}, {"lat": -26.60316, "lng": -65.9127, "km": 16.5}, {"lat": -26.602, "lng": -65.91398, "km": 16.6}, {"lat": -26.60084, "lng": -65.91525, "km": 16.8}, {"lat": -26.59968, "lng": -65.91653, "km": 17.0}, {"lat": -26.59851, "lng": -65.9178, "km": 17.2}, {"lat": -26.59735, "lng": -65.91907, "km": 17.4}, {"lat": -26.59619, "lng": -65.92035, "km": 17.5}, {"lat": -26.59503, "lng": -65.92162, "km": 17.7}, {"lat": -26.59387, "lng": -65.9229, "km": 17.9}]}